niota/__init__.py
niota/encoder.py
niota/exceptions.py
niota/iota_client.py
niota/models.py
niota/niota.py
niota/signature.py
niota-0.8.0.dist-info/METADATA
niota-0.8.0.dist-info/WHEEL
niota-0.8.0.dist-info/top_level.txt
niota-0.8.0.dist-info/zip-safe
niota-0.8.0.dist-info/RECORD
