Metadata-Version: 2.1
Name: niota
Version: 0.8.0
Summary: Numbers IOTA tool
Home-page: https://github.com/numbersprotocol/niota
Author: Numbers Co., Inc
Author-email: hi@numbersprotocol.io
License: UNKNOWN
Platform: UNKNOWN
Classifier: Development Status :: 4 - Beta
Classifier: License :: OSI Approved :: GNU General Public License v3 (GPLv3)
Classifier: Programming Language :: Python :: 3
Requires-Python: >=3.6
Requires-Dist: cryptography
Requires-Dist: pycryptodome
Requires-Dist: pydantic
Requires-Dist: requests
Provides-Extra: docs
Requires-Dist: sphinx ; extra == 'docs'
Provides-Extra: tests
Requires-Dist: tox ; extra == 'tests'
